rmlib/__init__.py
rmlib/elem_set.py
rmlib/item.py
rmlib/util.py
rmlib-0.1.4.dist-info/METADATA
rmlib-0.1.4.dist-info/WHEEL
rmlib-0.1.4.dist-info/top_level.txt
rmlib-0.1.4.dist-info/RECORD
