Metadata-Version: 2.4
Name: rmlib
Version: 0.1.4
Summary: Shared utility library for Blender addons
Author-email: Timothee Yeramian <lead.acrysoft@gmail.com>
Requires-Python: >=3.7
